prismtoolbox/__init__.py
prismtoolbox/_logging.py
prismtoolbox/cli/main.py
prismtoolbox/cli/preprocessing.py
prismtoolbox/cli/utils.py
prismtoolbox/nucleiseg/__init__.py
prismtoolbox/nucleiseg/models/__init__.py
prismtoolbox/nucleiseg/models/sop/__init__.py
prismtoolbox/nucleiseg/models/sop/architectures.py
prismtoolbox/nucleiseg/models/sop/modules.py
prismtoolbox/nucleiseg/models/sop/postprocessing.py
prismtoolbox/nucleiseg/seg_utils.py
prismtoolbox/nucleiseg/segmenter.py
prismtoolbox/utils/__init__.py
prismtoolbox/utils/data_utils.py
prismtoolbox/utils/qupath_utils.py
prismtoolbox/utils/stain_utils.py
prismtoolbox/utils/torch_utils.py
prismtoolbox/utils/vis_utils.py
prismtoolbox/wsicore/__init__.py
prismtoolbox/wsicore/core_utils.py
prismtoolbox/wsicore/wsi.py
prismtoolbox/wsiemb/__init__.py
prismtoolbox/wsiemb/emb_utils.py
prismtoolbox/wsiemb/embedder.py
prismtoolbox/wsiemb/models/__init__.py
prismtoolbox/wsiemb/models/clam.py
prismtoolbox/wsiemb/models/conch_model/__init__.py
prismtoolbox/wsiemb/models/conch_model/coca_model.py
prismtoolbox/wsiemb/models/conch_model/conch.py
prismtoolbox/wsiemb/models/conch_model/config.json
prismtoolbox/wsiemb/models/conch_model/transformer.py
prismtoolbox/wsiemb/models/conch_model/utils.py
prismtoolbox/wsiemb/models/conch_model/vision_tower.py
prismtoolbox/wsiemb/models/generic.py
prismtoolbox/wsiemb/models/pathoduet.py
prismtoolbox/wsiemb/models/phikon.py
prismtoolbox/wsiemb/models/utils.py
prismtoolbox/wsiemb/processing.py
prismtoolbox-0.2.0.dist-info/LICENSE
prismtoolbox-0.2.0.dist-info/METADATA
prismtoolbox-0.2.0.dist-info/WHEEL
prismtoolbox-0.2.0.dist-info/entry_points.txt
prismtoolbox-0.2.0.dist-info/RECORD
