Metadata-Version: 2.3
Name: prismtoolbox
Version: 0.2.0
Summary: Toolbox for histopathology image analysis
License: BSD-3-Clause
Author: Loïc Le Bescond
Author-email: loic.le.bescond@centralesupelec.fr
Requires-Python: >=3.9,<3.13
Classifier: License :: OSI Approved :: BSD License
Classifier: Programming Language :: Python :: 3
Classifier: Programming Language :: Python :: 3.9
Classifier: Programming Language :: Python :: 3.10
Classifier: Programming Language :: Python :: 3.11
Classifier: Programming Language :: Python :: 3.12
Provides-Extra: emb
Provides-Extra: seg
Requires-Dist: cellpose (>=3.0.7,<4.0.0) ; extra == "seg"
Requires-Dist: dask[dataframe] (>=2024.3.1,<2025.0.0) ; extra == "emb"
Requires-Dist: geopandas (>=1.0.1,<2.0.0)
Requires-Dist: h5py (>=3.10.0,<4.0.0)
Requires-Dist: huggingface-hub (>=0.22.1,<0.23.0) ; extra == "emb"
Requires-Dist: ipywidgets (>=8.1.2,<9.0.0) ; extra == "seg"
Requires-Dist: matplotlib (>=3.8.3,<4.0.0)
Requires-Dist: numpy (>=1.26.4,<2.0.0)
Requires-Dist: opencv-python (>=4.8.1.78,<5.0.0.0)
Requires-Dist: openslide-python (>=1.3.1,<2.0.0)
Requires-Dist: pandas (>=2.2.1,<3.0.0)
Requires-Dist: scikit-image (>=0.24.0,<0.25.0) ; extra == "emb"
Requires-Dist: scikit-learn (>=1.4.1.post1,<2.0.0) ; extra == "emb"
Requires-Dist: scipy (>=1.12.0,<2.0.0)
Requires-Dist: shapely (>=2.0.3,<3.0.0)
Requires-Dist: tiffslide (>=2.3.0,<3.0.0)
Requires-Dist: timm (>=0.9.16,<0.10.0) ; extra == "emb"
Requires-Dist: torch (>=2.2.2,<3.0.0) ; extra == "emb" or extra == "seg"
Requires-Dist: torchvision (>=0.17.2,<0.18.0) ; extra == "emb" or extra == "seg"
Requires-Dist: tqdm (>=4.66.2,<5.0.0) ; extra == "emb"
Requires-Dist: transformers (>=4.38.2,<5.0.0) ; extra == "emb"
Requires-Dist: typer (>=0.16.0,<0.17.0)
Requires-Dist: umap-learn (>=0.5.5,<0.6.0) ; extra == "emb"
Requires-Dist: uuid (>=1.30,<2.0)
Project-URL: Documentation, https://gustaveroussy.github.io/prismtoolbox
Project-URL: Homepage, https://gustaveroussy.github.io/prismtoolbox
Project-URL: Repository, https://github.com/gustaveroussy/prismtoolbox
